kthbuild.py
kthbuild-0.0.26.dist-info/LICENSE
kthbuild-0.0.26.dist-info/METADATA
kthbuild-0.0.26.dist-info/WHEEL
kthbuild-0.0.26.dist-info/dependency_links.txt
kthbuild-0.0.26.dist-info/top_level.txt
kthbuild-0.0.26.dist-info/RECORD
